odoo/addons/account_avatax_oca_log/README.rst
odoo/addons/account_avatax_oca_log/__init__.py
odoo/addons/account_avatax_oca_log/__manifest__.py
odoo/addons/account_avatax_oca_log/data/cron.xml
odoo/addons/account_avatax_oca_log/data/emails.xml
odoo/addons/account_avatax_oca_log/i18n/account_avatax_oca_log.pot
odoo/addons/account_avatax_oca_log/i18n/it.po
odoo/addons/account_avatax_oca_log/models/__init__.py
odoo/addons/account_avatax_oca_log/models/avalara_salestax.py
odoo/addons/account_avatax_oca_log/models/avatax_log.py
odoo/addons/account_avatax_oca_log/models/avatax_rest_api.py
odoo/addons/account_avatax_oca_log/models/res_config_settings.py
odoo/addons/account_avatax_oca_log/readme/CONTRIBUTORS.md
odoo/addons/account_avatax_oca_log/readme/DESCRIPTION.md
odoo/addons/account_avatax_oca_log/readme/USAGE.md
odoo/addons/account_avatax_oca_log/security/ir.model.access.csv
odoo/addons/account_avatax_oca_log/static/description/icon.png
odoo/addons/account_avatax_oca_log/static/description/index.html
odoo/addons/account_avatax_oca_log/views/avatax_log_views.xml
odoo/addons/account_avatax_oca_log/views/res_config_settings_views.xml
odoo_addon_account_avatax_oca_log-18.0.1.0.0.5.dist-info/METADATA
odoo_addon_account_avatax_oca_log-18.0.1.0.0.5.dist-info/WHEEL
odoo_addon_account_avatax_oca_log-18.0.1.0.0.5.dist-info/top_level.txt
odoo_addon_account_avatax_oca_log-18.0.1.0.0.5.dist-info/RECORD
